fixedpoint/__init__.py
fixedpoint/fixedpoint.py
fixedpoint/functions.py
fixedpoint/json.py
fixedpoint/logging.py
fixedpoint/properties.py
fixedpoint/py.typed
fixedpoint-1.0.1.dist-info/DESCRIPTION.rst
fixedpoint-1.0.1.dist-info/LICENSE.txt
fixedpoint-1.0.1.dist-info/METADATA
fixedpoint-1.0.1.dist-info/RECORD
fixedpoint-1.0.1.dist-info/WHEEL
fixedpoint-1.0.1.dist-info/metadata.json
fixedpoint-1.0.1.dist-info/top_level.txt
