Metadata-Version: 2.0
Name: fixedpoint
Version: 1.0.1
Summary: Fixed point arithmetic library
Home-page: https://fixedpoint.readthedocs.io/
Author: Zack Sheffield
Author-email: zack_sheffield@selinc.com
Maintainer: Zack Sheffield
Maintainer-email: zack_sheffield@selinc.com
License: BSD
Download-URL: https://pypi.org/project/fixedpoint/
Project-URL: Bug Tracker, https://github.com/Schweitzer-Engineering-Laboratories/fixedpoint/issues
Project-URL: Documentation, https://fixedpoint.readthedocs.io/
Project-URL: Source Code, https://github.com/Schweitzer-Engineering-Laboratories/fixedpoint
Keywords: fixed-point,arithmetic,binary,bit-accurate
Platform: UNKNOWN
Classifier: Development Status :: 5 - Production/Stable
Classifier: License :: OSI Approved :: BSD License
Classifier: Natural Language :: English
Classifier: Intended Audience :: Developers
Classifier: Intended Audience :: Education
Classifier: Intended Audience :: Science/Research
Classifier: Programming Language :: Python :: 3.8
Classifier: Topic :: Scientific/Engineering
Classifier: Topic :: Scientific/Engineering :: Mathematics
Classifier: Topic :: Software Development :: Embedded Systems
Classifier: Typing :: Typed
Requires-Python: >=3.8
Provides-Extra: docs
Provides-Extra: test_dependencies
Provides-Extra: docs
Requires-Dist: sphinx (==2.4.4); extra == 'docs'
Requires-Dist: sphinx-rtd-theme (==0.4.3); extra == 'docs'
Provides-Extra: test_dependencies
Requires-Dist: nose (>=1.3.7); extra == 'test_dependencies'
Requires-Dist: coverage (>=5.0.3); extra == 'test_dependencies'
Requires-Dist: mypy (>=0.761); extra == 'test_dependencies'
Requires-Dist: tqdm (>=4.43.0); extra == 'test_dependencies'
Requires-Dist: sphinx (==2.4.4); extra == 'test_dependencies'
Requires-Dist: sphinx-rtd-theme (==0.4.3); extra == 'test_dependencies'
Requires-Dist: numpy (>=1.18.1); extra == 'test_dependencies'
